exert.cpython-37m-i386-linux-gnu.so
exert-0.3.3.dist-info/LICENSE
exert-0.3.3.dist-info/top_level.txt
exert-0.3.3.dist-info/WHEEL
exert-0.3.3.dist-info/RECORD
exert-0.3.3.dist-info/METADATA
exert/py.typed
exert/__init__.py
examples/mixed.py
examples/validation.py
examples/__init__.py
