Metadata-Version: 2.1
Name: exert
Version: 0.3.3
Summary: Declarively apply converter functions to class attributes.
Home-page: https://github.com/rednafi/exert
Author: Redowan Delowar
Author-email: redowan.nafi@gmail.com
License: MIT
Classifier: License :: OSI Approved :: MIT License
Classifier: Programming Language :: Python :: 3
Classifier: Programming Language :: Python :: 3 :: Only
Classifier: Programming Language :: Python :: 3.7
Classifier: Programming Language :: Python :: 3.8
Classifier: Programming Language :: Python :: 3.9
Classifier: Programming Language :: Python :: 3.10
Classifier: Programming Language :: Python :: Implementation :: CPython
Requires-Python: >=3.7.0
Provides-Extra: dev_deps
License-File: LICENSE
